[
  {
    "name": "Åhlens",
    "url": "ahlens.se/varuhus/jonkoping?utm_source=google&utm_medium=organic&utm_campaign=business_profile&utm_content=website_link",
    "district": "Öster",
    "categories": "Shoppa",
    "subCategory": "Apparel",
    "openingTime": "09:00",
    "closingTime": "18:00",
    "contact": {
      "phone": "123-456-7890",
      "email": "info@åhlens.com"
    },
    "rating": 4
  },
  {
    "name": "Akademibokhandeln",
    "url": "akademibokhandeln.se/butik/jonkoping-c",
    "district": "Öster",
    "categories": "Upplev",
    "subCategory": "Museums and Culture",
    "openingTime": "09:00",
    "closingTime": "18:00",
    "contact": {
      "phone": "123-456-7890",
      "email": "info@akademibokhandeln.com"
    },
    "rating": 3.4
  },
  {
    "name": "Apoteket AB",
    "url": "apoteket.se/apotek/apoteket-ostra-storgatan-jonkoping/",
    "district": "Öster",
    "categories": "Shoppa",
    "subCategory": "Health and Beauty",
    "openingTime": "09:00",
    "closingTime": "18:00",
    "contact": {
      "phone": "123-456-7890",
      "email": "info@apoteket.com"
    },
    "rating": 5
  },
  {
    "name": "Apotek Hjärtat",
    "url": "apotekhjartat.se/hitta-apotek-hjartat/jonkoping/apotek_hjartat_smedjegatan_2_jonkoping/",
    "district": "Öster",
    "categories": "Shoppa",
    "subCategory": "Health and Beauty",
    "openingTime": "09:00",
    "closingTime": "18:00",
    "contact": {
      "phone": "123-456-7890",
      "email": "info@apotek_hjärtat.com"
    },
    "rating": 4.5
  },
  {
    "name": "Ashur Brud & Fest - Skrädderi",
    "url": "facebook.com/AshuraitaBrudFest/",
    "district": "Väster",
    "categories": "Shoppa",
    "subCategory": "Apparel",
    "openingTime": "09:00",
    "closingTime": "18:00",
    "contact": {
      "phone": "123-556-7890",
      "email": "info@ashur.com"
    },
    "rating": 4
  },
  {
    "name": "Asia livs, servicebutik",
    "url": "facebook.com/profile.php?id=100051215441977",
    "district": "Väster",
    "categories": "Shoppa",
    "subCategory": "Grocery",
    "openingTime": "09:00",
    "closingTime": "18:00",
    "contact": {
      "phone": "123-456-7890",
      "email": "info@asia.com"
    },
    "rating": 3
  },
  {
    "name": "Ateljé Creativ i Jönköping/Finrummet",
    "url": "/finrummet.net",
    "district": "Väster",
    "categories": "Upplev",
    "subCategory": "Museums and Culture",
    "openingTime": "09:00",
    "closingTime": "18:00",
    "contact": {
      "phone": "122-456-7890",
      "email": "info@ateljé.com"
    },
    "rating": 3
  },
  {
    "name": "Ateljé KEG",
    "url": "ateljekeg.se",
    "district": "Öster",
    "categories": "Shoppa",
    "subCategory": "Apparel",
    "openingTime": "09:00",
    "closingTime": "18:00",
    "contact": {
      "phone": "123-456-7892",
      "email": "info@ateljé.com"
    },
    "rating": 4
  },
  {
    "name": "Atlantis Dive College",
    "url": "atlantis.se",
    "district": "Väster",
    "categories": "Upplev",
    "subCategory": "Entertainment and Activities",
    "openingTime": "09:00",
    "closingTime": "18:00",
    "contact": {
      "phone": "123-456-7890",
      "email": "info@atlantis.com"
    },
    "rating": 5
  },
  {
    "name": "Bagelle väskboutique",
    "url": "Bagelle.com",
    "district": "Väster",
    "categories": "Shoppa",
    "subCategory": "Apparel",
    "openingTime": "09:00",
    "closingTime": "18:00",
    "contact": {
      "phone": "123-456-7897",
      "email": "info@bagelle.com"
    },
    "rating": 4
  },
  {
    "name": "Balance Ljud och Bild",
    "url": "balance.se",
    "district": "Väster",
    "categories": "Shoppa",
    "subCategory": "Electronics",
    "openingTime": "09:00",
    "closingTime": "18:00",
    "contact": {
      "phone": "123-456-7590",
      "email": "info@balance.com"
    },
    "rating": 4
  },
  {
    "name": "BGA Fotocenter",
    "url": "bgafotocenter.se/jonkoping/",
    "district": "Öster",
    "categories": "Upplev",
    "subCategory": "Entertainment and Activities",
    "openingTime": "09:00",
    "closingTime": "18:00",
    "contact": {
      "phone": "123-456-7870",
      "email": "info@bgafotocenter.com"
    },
    "rating": 3
  },
  {
    "name": "Bikupan",
    "url": "bikupan.org",
    "district": "Tändsticksområdet",
    "categories": "Må bra",
    "subCategory": "Health and Wellness",
    "openingTime": "09:00",
    "closingTime": "18:00",
    "contact": {
      "phone": "123-756-7890",
      "email": "info@bikupan.com"
    },
    "rating": 3
  },
  {
    "name": "Blankdays",
    "url": "https://blankdays.com/collections/all-products?gclid=CjwKCAjwov6hBhBsEiwAvrvN6EZZ1PsnlSJhnE7bmxINtl0Y0noU3rvCybdt217CGd3-bqMdx3mYRxoCK5EQAvD_BwE",
    "district": "Tändsticksområdet",
    "categories": "Shoppa",
    "subCategory": "Apparel",
    "openingTime": "09:00",
    "closingTime": "18:00",
    "contact": {
      "phone": "123-456-7890",
      "email": "info@blankdays.com"
    },
    "rating": 4
  },
  {
    "name": "Boardlife",
    "url": "boardlife.se",
    "district": "Väster",
    "categories": "Upplev",
    "subCategory": "Entertainment and Activities",
    "openingTime": "09:00",
    "closingTime": "18:00",
    "contact": {
      "phone": "123-456-7190",
      "email": "info@boardlife.com"
    },
    "rating": 4
  },
  {
    "name": "Borgs skor",
    "url": "borgsskor.se/kontakt",
    "district": "Öster",
    "categories": "Shoppa",
    "subCategory": "Apparel",
    "openingTime": "09:00",
    "closingTime": "18:00",
    "contact": {
      "phone": "123-456-7890",
      "email": "info@borgsskor.com"
    },
    "rating": 4
  },
  {
    "name": "Boutique Lykka",
    "url": "boutiquelykka.se",
    "district": "Öster",
    "categories": "Shoppa",
    "subCategory": "Apparel",
    "openingTime": "09:00",
    "closingTime": "18:00",
    "contact": {
      "phone": "123-456-7890",
      "email": "info@boutiquelykka.com"
    },
    "rating": 5
  },
  {
    "name": "Broder Bläck",
    "url": "facebook.com/broderblacktatuering/",
    "district": "Öster",
    "categories": "Må bra",
    "subCategory": "Beauty Salons and Nail Bars",
    "openingTime": "09:00",
    "closingTime": "18:00",
    "contact": {
      "phone": "123-456-4890",
      "email": "info@broder.com"
    },
    "rating": 3
  },
  {
    "name": "Buketten",
    "url": "instagram.com/bukettenjonkoping/?hl=sv",
    "district": "Öster",
    "categories": "Shoppa",
    "subCategory": "Home and Decor",
    "openingTime": "09:00",
    "closingTime": "18:00",
    "contact": {
      "phone": "123-457-7890",
      "email": "info@buketten.com"
    },
    "rating": 4
  },
  {
    "name": "Busfrö Nytt & Bytt",
    "url": "busfro.se",
    "district": "Öster",
    "categories": "Shoppa",
    "subCategory": "Apparel",
    "openingTime": "09:00",
    "closingTime": "18:00",
    "contact": {
      "phone": "123-456-7190",
      "email": "info@busfro.com"
    },
    "rating": 4
  },
  {
    "name": "Butiken Noga Utvalt",
    "url": "butikenjkpg.se",
    "district": "Atollen",
    "categories": "Shoppa",
    "subCategory": "Apparel",
    "openingTime": "09:00",
    "closingTime": "18:00",
    "contact": {
      "phone": "123-456-7894",
      "email": "info@butikenjkpg.com"
    },
    "rating": 4
  },
  {
    "name": "Carlings",
    "url": "carlings.com/sv/corporate/Butiker/sweden/58f/",
    "district": "Öster",
    "categories": "Shoppa",
    "subCategory": "Apparel",
    "openingTime": "09:00",
    "closingTime": "18:00",
    "contact": {
      "phone": "123-456-7890",
      "email": "info@carlings.com"
    },
    "rating": 3
  },
  {
    "name": "Casa Souk",
    "url": "casasouk.se",
    "district": "Väster",
    "categories": "Shoppa",
    "subCategory": "Health and Beauty",
    "openingTime": "09:00",
    "closingTime": "18:00",
    "contact": {
      "phone": "143-456-7890",
      "email": "info@casasouk.com"
    },
    "rating": 4
  },
  {
    "name": "Cervera",
    "url": "cervera.se/hitta-butik/",
    "district": "Öster",
    "categories": "Shoppa",
    "subCategory": "Home and Decor",
    "openingTime": "09:00",
    "closingTime": "18:00",
    "contact": {
      "phone": "123-456-7870",
      "email": "info@cervera.com"
    },
    "rating": 4
  },
  {
    "name": "Clas Ohlson",
    "url": "clasohlson.com/se/store-finder?q=J%C3%B6nk%C3%B6ping,%20City&latitude=57.78252&longitude=14.17347&source=search",
    "district": "Öster",
    "categories": "Shoppa",
    "subCategory": "Home and Decor",
    "openingTime": "09:00",
    "closingTime": "18:00",
    "contact": {
      "phone": "123-456-7890",
      "email": "info@clasohlson.com"
    },
    "rating": 4
  },
  {
    "name": "Coop Atollen",
    "url": "coop.se/butiker-erbjudanden/coop/coop-atollen-jonkoping/",
    "district": "Atollen",
    "categories": "Shoppa",
    "subCategory": "Grocery",
    "openingTime": "09:00",
    "closingTime": "18:00",
    "contact": {
      "phone": "123-456-7890",
      "email": "info@coop.com"
    },
    "rating": 5
  },
  {
    "name": "Coop Östra Torget",
    "url": "coop.se/butiker-erbjudanden/coop/coop-ostra-torget/",
    "district": "Öster",
    "categories": "Shoppa",
    "subCategory": "Grocery",
    "openingTime": "09:00",
    "closingTime": "18:00",
    "contact": {
      "phone": "123-456-7897",
      "email": "info@coop.com"
    },
    "rating": 5
  },
  {
    "name": "Copenhagen Luxe",
    "url": "https://copenhagenluxe.dk/",
    "district": "Öster",
    "categories": "Shoppa",
    "subCategory": "Apparel",
    "openingTime": "09:00",
    "closingTime": "18:00",
    "contact": {
      "phone": "123-486-7890",
      "email": "info@copenhagen.com"
    },
    "rating": 4
  },
  {
    "name": "Day fotografi",
    "url": "dayfotografi.se/",
    "district": "Öster",
    "categories": "Upplev",
    "subCategory": "Entertainment and Activities",
    "openingTime": "09:00",
    "closingTime": "18:00",
    "contact": {
      "phone": "123-456-7890",
      "email": "info@dayfotografi.com"
    },
    "rating": 4
  },
  {
    "name": "Dinos kemtvätt",
    "url": "dinos.nu",
    "district": "Väster",
    "categories": "Shoppa",
    "subCategory": "Apparel",
    "openingTime": "09:00",
    "closingTime": "18:00",
    "contact": {
      "phone": "123-456-7190",
      "email": "info@dinos.com"
    },
    "rating": 4
  },
  {
    "name": "Din Sko",
    "url": "dinsko.se/stores",
    "district": "Öster",
    "categories": "Shoppa",
    "subCategory": "Apparel",
    "openingTime": "09:00",
    "closingTime": "18:00",
    "contact": {
      "phone": "123-456-7820",
      "email": "info@dinsko.com"
    },
    "rating": 4
  },
  {
    "name": "Direkt optik",
    "url": "https://www.direktoptik.se/butiker/jonkoping/ostra-storgatan-29/",
    "district": "Öster",
    "categories": "Shoppa",
    "subCategory": "Health and Beauty",
    "openingTime": "09:00",
    "closingTime": "18:00",
    "contact": {
      "phone": "123-456-7890",
      "email": "info@direktoptik.com"
    },
    "rating": 4
  },
  {
    "name": "Dressman",
    "url": "dressmann.com/no/bedriftssider/finn-butikk/Sweden/Dressmann_Jonkoping/",
    "district": "Öster",
    "categories": "Shoppa",
    "subCategory": "Apparel",
    "openingTime": "09:00",
    "closingTime": "18:00",
    "contact": {
      "phone": "123-456-7790",
      "email": "info@dressmann.com"
    },
    "rating": 4
  },
  {
    "name": "Elias Urmästare",
    "url": "facebook.com/profile.php?id=100064073112753",
    "district": "Väster",
    "categories": "Shoppa",
    "subCategory": "Apparel",
    "openingTime": "09:00",
    "closingTime": "18:00",
    "contact": {
      "phone": "123-456-7810",
      "email": "info@elias.com"
    },
    "rating": 4
  },
  {
    "name": "Engströms Urmakeri",
    "url": "engstromsurmakeri.se",
    "district": "Öster",
    "categories": "Shoppa",
    "subCategory": "Apparel",
    "openingTime": "09:00",
    "closingTime": "18:00",
    "contact": {
      "phone": "123-456-7810",
      "email": "info@engstromsurmakeri.com"
    },
    "rating": 5
  },
  {
    "name": "Euroex",
    "url": "euroex.com",
    "district": "Väster",
    "categories": "Upplev",
    "subCategory": "Museums and Culture",
    "openingTime": "09:00",
    "closingTime": "18:00",
    "contact": {
      "phone": "123-456-7890",
      "email": "info@euroex.com"
    },
    "rating": 5
  },
  {
    "name": "Evoke industry",
    "url": "evoke.com",
    "district": "Väster",
    "categories": "Upplev",
    "subCategory": "Museums and Culture",
    "openingTime": "09:00",
    "closingTime": "18:00",
    "contact": {
      "phone": "123-456-7890",
      "email": "example@evoke.com"
    },
    "rating": 5
  },
  {
    "name": "Fabriken",
    "url": "butikfabriken.se",
    "district": "Atollen",
    "categories": "Shoppa",
    "subCategory": "Apparel",
    "openingTime": "09:00",
    "closingTime": "18:00",
    "contact": {
      "phone": "123-456-7890",
      "email": "info@butikfabriken.com"
    },
    "rating": 4
  },
  {
    "name": "Fiction Prescription",
    "url": "https://www.instagram.com/fiction.prescription.jonkoping/",
    "district": "Väster",
    "categories": "Upplev",
    "subCategory": "Entertainment and Activities",
    "openingTime": "09:00",
    "closingTime": "18:00",
    "contact": {
      "phone": "123-456-7890",
      "email": "info@fiction.com"
    },
    "rating": 4
  },
  {
    "name": "Forex Bank Väster",
    "url": "forex.com",
    "district": "Väster",
    "categories": "Upplev",
    "subCategory": "Museums and Culture",
    "openingTime": "09:00",
    "closingTime": "18:00",
    "contact": {
      "phone": "123-456-7890",
      "email": "info@forex.com"
    },
    "rating": 5
  },
  {
    "name": "Foten",
    "url": "https://www.foten.se/",
    "district": "Väster",
    "categories": "Må bra",
    "subCategory": "Health and Wellness",
    "openingTime": "09:00",
    "closingTime": "18:00",
    "contact": {
      "phone": "123-456-7897",
      "email": "info@foten.com"
    },
    "rating": 5
  },
  {
    "name": "Friendly Corner",
    "url": "https://friendlycorner.se/butiken",
    "district": "Tändsticksområdet",
    "categories": "Shoppa",
    "subCategory": "Home and Decor",
    "openingTime": "09:00",
    "closingTime": "18:00",
    "contact": {
      "phone": "123-456-7890",
      "email": "example@email.com"
    },
    "rating": 4
  },
  {
    "name": "Galleri 701 ramcenter",
    "url": "galleri701-ram.se",
    "district": "Väster",
    "categories": "Upplev",
    "subCategory": "Museums and Culture",
    "openingTime": "09:00",
    "closingTime": "18:00",
    "contact": {
      "phone": "123-456-7890",
      "email": "info@galleri701.com"
    },
    "rating": 5
  },
  {
    "name": "Gant",
    "url": "gant.se/stores?lat=57.78261370000001&long=14.1617876&postalCode=j%C3%B6nk%C3%B6ping&radius=10.0",
    "district": "Atollen",
    "categories": "Shoppa",
    "subCategory": "Apparel",
    "openingTime": "09:00",
    "closingTime": "18:00",
    "contact": {
      "phone": "123-456-7890",
      "email": "info@gant.com"
    },
    "rating": 4
  },
  {
    "name": "Gåvan",
    "url": "gavanjonkoping.se",
    "district": "Öster",
    "categories": "Shoppa",
    "subCategory": "Apparel",
    "openingTime": "09:00",
    "closingTime": "18:00",
    "contact": {
      "phone": "123-476-7890",
      "email": "example@gåvan.com"
    },
    "rating": 4
  },
  {
    "name": "Gina Tricot",
    "url": "ginatricot.com/se/find-store",
    "district": "Öster",
    "categories": "Shoppa",
    "subCategory": "Apparel",
    "openingTime": "09:00",
    "closingTime": "18:00",
    "contact": {
      "phone": "123-456-7890",
      "email": "example@email.com"
    },
    "rating": 5
  },
  {
    "name": "Go Banana",
    "url": "gobanana.se",
    "district": "Väster",
    "categories": "Äta",
    "subCategory": "Fast Food",
    "openingTime": "09:00",
    "closingTime": "18:00",
    "contact": {
      "phone": "123-456-7890",
      "email": "info@gobanana.com"
    },
    "rating": 4
  },
  {
    "name": "Godis och Tobakshörnan",
    "url": "godis.com",
    "district": "Öster",
    "categories": "Shoppa",
    "subCategory": "Grocery",
    "openingTime": "09:00",
    "closingTime": "18:00",
    "contact": {
      "phone": "123-456-7897",
      "email": "info@godis.com"
    },
    "rating": 4
  },
  {
    "name": "Golden athlete",
    "url": "goldenathlete.se/sv/butiker-2",
    "district": "Öster",
    "categories": "Må bra",
    "subCategory": "Health and Wellness",
    "openingTime": "09:00",
    "closingTime": "18:00",
    "contact": {
      "phone": "123-476-7890",
      "email": "info@golden.com"
    },
    "rating": 4
  },
  {
    "name": "Grmawit Store",
    "url": "grmawit.com/",
    "district": "Väster",
    "categories": "Shoppa",
    "subCategory": "Apparel",
    "openingTime": "09:00",
    "closingTime": "18:00",
    "contact": {
      "phone": "123-456-7890",
      "email": "info@grmawit.com"
    },
    "rating": 4
  },
  {
    "name": "Guldsmedjan Snarberg",
    "url": "guldsmedjan-snarberg.se",
    "district": "Väster",
    "categories": "Sova",
    "subCategory": "Hotels",
    "openingTime": "09:00",
    "closingTime": "18:00",
    "contact": {
      "phone": "123-456-7891",
      "email": "info@guldsmedjan.com"
    },
    "rating": 5
  },
  {
    "name": "Hälsokraft",
    "url": "halsokraft.se/butiker?butik=503",
    "district": "Öster",
    "categories": "Shoppa",
    "subCategory": "Health and Beauty",
    "openingTime": "09:00",
    "closingTime": "18:00",
    "contact": {
      "phone": "098-456-7890",
      "email": "halsokraft@email.com"
    },
    "rating": 5
  },
  {
    "name": "Hemköp",
    "url": "hemkop.se/butik/4674",
    "district": "Väster",
    "categories": "Shoppa",
    "subCategory": "Grocery",
    "openingTime": "09:00",
    "closingTime": "23:00",
    "contact": {
      "phone": "094-456-7890",
      "email": "hemkop@email.com"
    },
    "rating": 3
  },
  {
    "name": "Hemmakväll",
    "url": "hemmakvall.se/hitta-butik/",
    "district": "Öster",
    "categories": "Shoppa",
    "subCategory": "Grocery",
    "openingTime": "09:00",
    "closingTime": "18:00",
    "contact": {
      "phone": "087-456-7890",
      "email": "hemmakvall@email.com"
    },
    "rating": 5
  },
  {
    "name": "Hemtex",
    "url": "hemtex.se/hitta-butik/jonkoping",
    "district": "Öster",
    "categories": "Shoppa",
    "subCategory": "Home and Decor",
    "openingTime": "09:00",
    "closingTime": "18:00",
    "contact": {
      "phone": "073-456-7890",
      "email": "hemtex@email.com"
    },
    "rating": 5
  },
  {
    "name": "Hi-fi Klubben",
    "url": "hifiklubben.se/hitta-butik/jonkoping/?gclid=Cj0KCQjwhsmaBhCvARIsAIbEbH4w2ngSDzygBKQSqHVzCSFAplyrpByCMojT6dfo-Xnjcn7P9j_jBn8aAsD0EALw_wcB",
    "district": "Väster",
    "categories": "Shoppa",
    "subCategory": "Electronics",
    "openingTime": "09:00",
    "closingTime": "18:00",
    "contact": {
      "phone": "073-456-7890",
      "email": "hifiklubben@email.com"
    },
    "rating": 3
  },
  {
    "name": "H&M",
    "url": "hm.com/sv_se/customer-service/shoppa-pa-hm/store-locator",
    "district": "Öster",
    "categories": "Shoppa",
    "subCategory": "Apparel",
    "openingTime": "09:00",
    "closingTime": "18:00",
    "contact": {
      "phone": "098-456-7890",
      "email": "hm@email.com"
    },
    "rating": 3
  },
  {
    "name": "H&M Home",
    "url": "hm.com/sv_se/customer-service/shoppa-pa-hm/store-locator",
    "district": "Öster",
    "categories": "Shoppa",
    "subCategory": "Home and Decor",
    "openingTime": "09:00",
    "closingTime": "18:00",
    "contact": {
      "phone": "073-456-7890",
      "email": "hm@email.com"
    },
    "rating": 2
  },
  {
    "name": "Indiska",
    "url": "indiska.com/se/butiker",
    "district": "Öster",
    "categories": "Shoppa",
    "subCategory": "Home and Decor",
    "openingTime": "09:00",
    "closingTime": "18:00",
    "contact": {
      "phone": "876-456-7890",
      "email": "indiska@email.com"
    },
    "rating": 5
  },
  {
    "name": "Jeansshoppen",
    "url": "jeansshopen.se/sv/kontakt",
    "district": "Öster",
    "categories": "Shoppa",
    "subCategory": "Apparel",
    "openingTime": "09:00",
    "closingTime": "18:00",
    "contact": {
      "phone": "123-456-7890",
      "email": "jeansshopen@email.com"
    },
    "rating": 3
  },
  {
    "name": "JL Sycenter",
    "url": "jlsycenter.se/kontakta-oss/",
    "district": "Öster",
    "categories": "Shoppa",
    "subCategory": "Electronics",
    "openingTime": "09:00",
    "closingTime": "18:00",
    "contact": {
      "phone": "654-456-7890",
      "email": "jlsycenter@email.com"
    },
    "rating": 3
  },
  {
    "name": "Jönköpings antik och konsthandel",
    "url": "jönköpingsantik.com",
    "district": "Väster",
    "categories": "Upplev",
    "subCategory": "Museums and Culture",
    "openingTime": "09:00",
    "closingTime": "18:00",
    "contact": {
      "phone": "098-456-7890",
      "email": "jönköpingsantik@email.com"
    },
    "rating": 5
  },
  {
    "name": "Jönköpings Cigrarrimport",
    "url": "atg.se/jonkopingscigarrimport",
    "district": "Väster",
    "categories": "Shoppa",
    "subCategory": "Grocery",
    "openingTime": "09:00",
    "closingTime": "18:00",
    "contact": {
      "phone": "765-456-7890",
      "email": "atg@email.com"
    },
    "rating": 2
  },
  {
    "name": "KappAhl",
    "url": "www.kappahl.com/sv-SE/kundservice/kundservice/hitta-butik/",
    "district": "Öster",
    "categories": "Shoppa",
    "subCategory": "Apparel",
    "openingTime": "09:00",
    "closingTime": "18:00",
    "contact": {
      "phone": "072-456-7890",
      "email": "info@kappahl.com"
    },
    "rating": 2
  },
  {
    "name": "Karin Lund Design",
    "url": "facebook.com/karinlunddesign/",
    "district": "Väster",
    "categories": "Shoppa",
    "subCategory": "Home and Decor",
    "openingTime": "09:00",
    "closingTime": "18:00",
    "contact": {
      "phone": "072-456-7890",
      "email": "info@email.com"
    },
    "rating": 4
  },
  {
    "name": "Katrin Bååths Ateljé",
    "url": "https://katrinbaath.se/ateljen/",
    "district": "Tändsticksområdet",
    "categories": "Upplev",
    "subCategory": "Home and Decor",
    "openingTime": "09:00",
    "closingTime": "18:00",
    "contact": {
      "phone": "072-456-7890",
      "email": "info@email.com"
    },
    "rating": 4
  },
  {
    "name": "Kicks",
    "url": "kicks.se/butiker/jonkoping-smedjegatan",
    "district": "Öster",
    "categories": "Shoppa",
    "subCategory": "Health and Beauty",
    "openingTime": "09:00",
    "closingTime": "18:00",
    "contact": {
      "phone": "072-456-7890",
      "email": "info@kicks.com"
    },
    "rating": 5
  },
  {
    "name": "Kjell & Company",
    "url": "kjell.com/se/butiker/sodra-strandgatan-5",
    "district": "Öster",
    "categories": "Shoppa",
    "subCategory": "Electronics",
    "openingTime": "09:00",
    "closingTime": "18:00",
    "contact": {
      "phone": "072-456-7890",
      "email": "info@email.com"
    },
    "rating": 3
  },
  {
    "name": "Klädscoopet",
    "url": "facebook.com/Kladscoopet/",
    "district": "Öster",
    "categories": "Shoppa",
    "subCategory": "Apparel",
    "openingTime": "09:00",
    "closingTime": "18:00",
    "contact": {
      "phone": "070-456-7890",
      "email": "info@email.com"
    },
    "rating": 2
  },
  {
    "name": "KOiJ Konsthantverk",
    "url": "koij.se",
    "district": "Öster",
    "categories": "Upplev",
    "subCategory": "Museums and Culture",
    "openingTime": "09:00",
    "closingTime": "18:00",
    "contact": {
      "phone": "070-456-7890",
      "email": "example@email.com"
    },
    "rating": 5
  },
  {
    "name": "Kristina Brud & Fest",
    "url": "kristinabrud-fest.se",
    "district": "Väster",
    "categories": "Shoppa",
    "subCategory": "Apparel",
    "openingTime": "09:00",
    "closingTime": "18:00",
    "contact": {
      "phone": "072-456-7890",
      "email": "info@email.com"
    },
    "rating": 1
  },
  {
    "name": "Kronans Apotek Atollen",
    "url": "apoteksinfo.nu/apotek/kronans_apotek_atollen_j%C3%B6nk%C3%B6ping-1415",
    "district": "Atollen",
    "categories": "Shoppa",
    "subCategory": "Health and Beauty",
    "openingTime": "09:00",
    "closingTime": "18:00",
    "contact": {
      "phone": "073-456-7890",
      "email": "example@email.com"
    },
    "rating": 4
  },
  {
    "name": "Kvänum Kök",
    "url": "kvanum.com/se/showrooms/jonkoping/",
    "district": "Öster",
    "categories": "Shoppa",
    "subCategory": "Home and Decor",
    "openingTime": "09:00",
    "closingTime": "18:00",
    "contact": {
      "phone": "073-456-7890",
      "email": "info@email.com"
    },
    "rating": 5
  },
  {
    "name": "Lagerhaus",
    "url": "lagerhaus.se/stores",
    "district": "Öster",
    "categories": "Shoppa",
    "subCategory": "Home and Decor",
    "openingTime": "09:00",
    "closingTime": "18:00",
    "contact": {
      "phone": "072-456-7890",
      "email": "info@email.com"
    },
    "rating": 5
  },
  {
    "name": "Lavér Studio",
    "url": "laverstudio.com/",
    "district": "Öster",
    "categories": "Shoppa",
    "subCategory": "Home and Decor",
    "openingTime": "09:00",
    "closingTime": "18:00",
    "contact": {
      "phone": "070-456-7890",
      "email": "info@email.com"
    },
    "rating": 5
  },
  {
    "name": "Life Naturlig Hälsa",
    "url": "https://www.lifebutiken.se/stores",
    "district": "Väster",
    "categories": "Äta",
    "subCategory": "Cafés",
    "openingTime": "09:00",
    "closingTime": "18:00",
    "contact": {
      "phone": "072-456-7890",
      "email": "info@email.com"
    },
    "rating": 1
  },
  {
    "name": "Lilla Violen",
    "url": "lillaviolen.com/",
    "district": "Väster",
    "categories": "Äta",
    "subCategory": "Fast Food",
    "openingTime": "09:00",
    "closingTime": "18:00",
    "contact": {
      "phone": "072-456-7890",
      "email": "info@email.com"
    },
    "rating": 5
  },
  {
    "name": "Lindex",
    "url": "lindex.com/se/hitta-din-butik?location=57.756066%2C14.188254&storeId=002&zoom=11",
    "district": "Öster",
    "categories": "Shoppa",
    "subCategory": "Apparel",
    "openingTime": "09:00",
    "closingTime": "18:00",
    "contact": {
      "phone": "072-456-7890",
      "email": "info@email.com"
    },
    "rating": 3
  },
  {
    "name": "Livspotential Kroppsterapi",
    "url": "facebook.com/Livspotential/",
    "district": "Öster",
    "categories": "Må bra",
    "subCategory": "Health and Wellness",
    "openingTime": "09:00",
    "closingTime": "18:00",
    "contact": {
      "phone": "072-456-7890",
      "email": "info@email.com"
    },
    "rating": 5
  },
  {
    "name": "Lloyd Tabing Art Gallery",
    "url": "lloydtabingart.com/",
    "district": "Tändsticksområdet",
    "categories": "Må bra",
    "subCategory": "Beauty Salons and Nail Bars",
    "openingTime": "09:00",
    "closingTime": "18:00",
    "contact": {
      "phone": "123-456-7890",
      "email": "info@email.com"
    },
    "rating": 4
  },
  {
    "name": "Macforum",
    "url": "macforum.se/butiker/forum-jonkoping",
    "district": "Öster",
    "categories": "Upplev",
    "subCategory": "Entertainment and Activities",
    "openingTime": "09:00",
    "closingTime": "18:00",
    "contact": {
      "phone": "123-456-7890",
      "email": "example@email.com"
    },
    "rating": 2
  },
  {
    "name": "MarQet",
    "url": "mq.se/butiker/?gclid=Cj0KCQjwteOaBhDuARIsADBqRejM-U3YQY9vh4F6gSXC2LnJWPVGKJ7CGfiCl1tYkREGUR37cTWMNcoaAjFGEALw_wcB",
    "district": "Öster",
    "categories": "Sova",
    "subCategory": "Hotels",
    "openingTime": "09:00",
    "closingTime": "18:00",
    "contact": {
      "phone": "073-456-7890",
      "email": "info@email.com"
    },
    "rating": 1
  },
  {
    "name": "Mimosa City",
    "url": "mimosacity.se",
    "district": "Väster",
    "categories": "Äta",
    "subCategory": "Fine Dinig",
    "openingTime": "09:00",
    "closingTime": "18:00",
    "contact": {
      "phone": "070-456-7890",
      "email": "info@email.com"
    },
    "rating": 5
  },
  {
    "name": "Moderna Smycken",
    "url": "klockorochsmycken.se/",
    "district": "Öster",
    "categories": "Shoppa",
    "subCategory": "Apparel",
    "openingTime": "09:00",
    "closingTime": "18:00",
    "contact": {
      "phone": "072-456-7890",
      "email": "info@email.com"
    },
    "rating": 0
  },
  {
    "name": "Naturkompaniet",
    "url": "murphysbar.se/sv/",
    "district": "Öster",
    "categories": "Shoppa",
    "subCategory": "Apparel",
    "openingTime": "09:00",
    "closingTime": "18:00",
    "contact": {
      "phone": "072-456-7890",
      "email": "info@naturkompaniet.com"
    },
    "rating": 4
  },
  {
    "name": "Newhouse",
    "url": "newhouse.se/newhouse/vara-butiker",
    "district": "Atollen",
    "categories": "Shoppa",
    "subCategory": "Apparel",
    "openingTime": "09:00",
    "closingTime": "17:00",
    "contact": {
      "phone": "072-456-7890",
      "email": "info@newhouse.com"
    },
    "rating": 3
  },
  {
    "name": "New Yorker",
    "url": "newyorker.de/se/stores/",
    "district": "Öster",
    "categories": "Shoppa",
    "subCategory": "Apparel",
    "openingTime": "09:00",
    "closingTime": "18:00",
    "contact": {
      "phone": "073-456-7890",
      "email": "info@newyorker.com"
    },
    "rating": 5
  },
  {
    "name": "Nilson Shoes",
    "url": "dinsko.se/stores",
    "district": "Öster",
    "categories": "Shoppa",
    "subCategory": "Apparel",
    "openingTime": "09:00",
    "closingTime": "18:00",
    "contact": {
      "phone": "072-456-7890",
      "email": "info@nilsonshoes.com"
    },
    "rating": 5
  },
  {
    "name": "Noa Noa",
    "url": "httpsfacebook.com/Noa-Noa-J%C3%B6nk%C3%B6ping-446212958766553/",
    "district": "Öster",
    "categories": "Shoppa",
    "subCategory": "Apparel",
    "openingTime": "09:00",
    "closingTime": "18:00",
    "contact": {
      "phone": "073-456-7890",
      "email": "info@noanoa.com"
    },
    "rating": 2
  },
  {
    "name": "Nordisk Möbelkonst",
    "url": "nordiskmobelkonst.se/",
    "district": "Öster",
    "categories": "Shoppa",
    "subCategory": "Home and Decor",
    "openingTime": "09:00",
    "closingTime": "18:00",
    "contact": {
      "phone": "123-456-7890",
      "email": "info@nordiskmobelkonst.com"
    },
    "rating": 5
  },
  {
    "name": "Normal",
    "url": "normal.se/hitta-butik/",
    "district": "Öster",
    "categories": "Shoppa",
    "subCategory": "Health and Beauty",
    "openingTime": "09:00",
    "closingTime": "18:00",
    "contact": {
      "phone": "123-456-7890",
      "email": "info@normal.com"
    },
    "rating": 5
  },
  {
    "name": "Nya Musik",
    "url": "nyamusik.se/",
    "district": "Väster",
    "categories": "Shoppa",
    "subCategory": "Electronics",
    "openingTime": "09:00",
    "closingTime": "18:00",
    "contact": {
      "phone": "072-456-7890",
      "email": "info@nyamusik.com"
    },
    "rating": 4
  },
  {
    "name": "Once for girls",
    "url": "oncestore.se/",
    "district": "Öster",
    "categories": "Shoppa",
    "subCategory": "Apparel",
    "openingTime": "09:00",
    "closingTime": "18:00",
    "contact": {
      "phone": "073-456-7890",
      "email": "info@onceforgirls.com"
    },
    "rating": 5
  },
  {
    "name": "Önska",
    "url": "onska.se/vara-butiker/",
    "district": "Öster",
    "categories": "Shoppa",
    "subCategory": "Home and Decor",
    "openingTime": "09:00",
    "closingTime": "18:00",
    "contact": {
      "phone": "072-456-7890",
      "email": "info@email.com"
    },
    "rating": 2
  },
  {
    "name": "Optiker Jahnke",
    "url": "jahnke.se/",
    "district": "Öster",
    "categories": "Må bra",
    "subCategory": "Heath and Wellness",
    "openingTime": "09:00",
    "closingTime": "18:00",
    "contact": {
      "phone": "072-456-7890",
      "email": "info@optikerjahnkeail.com"
    },
    "rating": 4
  },
  {
    "name": "Optiker Ullström",
    "url": "optikerullstrom.se/",
    "district": "Väster",
    "categories": "Må bra",
    "subCategory": "Heath and Wellness",
    "openingTime": "09:00",
    "closingTime": "18:00",
    "contact": {
      "phone": "072-456-7890",
      "email": "info@optikerullström.com"
    },
    "rating": 5
  },
  {
    "name": "Optik & Form",
    "url": "optikochform.se/",
    "district": "Väster",
    "categories": "Må bra",
    "subCategory": "Heath and Wellness",
    "openingTime": "09:00",
    "closingTime": "18:00",
    "contact": {
      "phone": "072-456-7890",
      "email": "info@optikandform.com"
    },
    "rating": 4
  },
  {
    "name": "Partyland",
    "url": "partyland.party/butiker/",
    "district": "Väster",
    "categories": "Shoppa",
    "subCategory": "Home and Decor",
    "openingTime": "09:00",
    "closingTime": "18:00",
    "contact": {
      "phone": "072-456-7890",
      "email": "info@partyland.com"
    },
    "rating": 5
  },
  {
    "name": "Planta Blommor",
    "url": "plantablommor.se/?gclid=Cj0KCQjwteOaBhDuARIsADBqRehsWXSRNHjeGnPn_AyambJZLmNntWxsMnUkANIHdme0NoDtc2Xi8mgaAicoEALw_wcB#.Y2p1tuzMLPZ",
    "district": "Väster",
    "categories": "Shoppa",
    "subCategory": "Home and Decor",
    "openingTime": "09:00",
    "closingTime": "18:00",
    "contact": {
      "phone": "072-456-7890",
      "email": "info@plantablommor.com"
    },
    "rating": 3
  },
  {
    "name": "Pleasure erotic shop",
    "url": "pleasureeroticshop.se/",
    "district": "Väster",
    "categories": "Shoppa",
    "subCategory": "Health and Beauty",
    "openingTime": "09:00",
    "closingTime": "18:00",
    "contact": {
      "phone": "072-456-7890",
      "email": "info@pleasureeroticshop.com"
    },
    "rating": 4
  },
  {
    "name": "PMU Second Hand Jönköping City",
    "url": "pmu.se/stores/jonkopingcity/",
    "district": "Öster",
    "categories": "Shoppa",
    "subCategory": "Apparel",
    "openingTime": "09:00",
    "closingTime": "18:00",
    "contact": {
      "phone": "072-456-7890",
      "email": "info@pmusecondhandjönköpingcity.com"
    },
    "rating": 4
  },
  {
    "name": "Pressbyrån Östra storgatan",
    "url": "pressbyran.se/kontakt/hitta-butik/",
    "district": "Öster",
    "categories": ["Unknown"],
    "subCategory": "Unknown",
    "openingTime": "09:00",
    "closingTime": "18:00",
    "contact": {
      "phone": "072-456-7890",
      "email": "example@email.com"
    },
    "rating": 3
  },
  {
    "name": "Pressbyrån Resecentrum",
    "url": "pressbyran.se/kontakt/hitta-butik/",
    "district": "Resecentrum",
    "categories": "Shoppa",
    "subCategory": "Grocery",
    "openingTime": "09:00",
    "closingTime": "18:00",
    "contact": {
      "phone": "072-456-7890",
      "email": "info@pressbyrånresecentrum.com"
    },
    "rating": 5
  },
  {
    "name": "Pressbyrån Väster",
    "url": "pressbyran.se/kontakt/hitta-butik/",
    "district": "Väster",
    "categories": "Shoppa",
    "subCategory": "Grocery",
    "openingTime": "09:00",
    "closingTime": "18:00",
    "contact": {
      "phone": "072-456-7890",
      "email": "info@pressbyrånväster.com"
    },
    "rating": 4
  },
  {
    "name": "Rabalder",
    "url": "publik.rabalder.se/butiker/joenkoeping.aspx",
    "district": "Öster",
    "categories": "Shoppa",
    "subCategory": "Apparel",
    "openingTime": "09:00",
    "closingTime": "18:00",
    "contact": {
      "phone": "073-456-7890",
      "email": "info@rabalder.com"
    },
    "rating": 1
  },
  {
    "name": "Resehuset",
    "url": "resehuset.se/",
    "district": "Väster",
    "categories": "Upplev",
    "subCategory": "Entertainment and Activities",
    "openingTime": "09:00",
    "closingTime": "18:00",
    "contact": {
      "phone": "070-456-7890",
      "email": "info@resehuset.com"
    },
    "rating": 3
  },
  {
    "name": "Rituals",
    "url": "rituals.com/sv-se/store-detail?store=J%C3%B6nk%C3%B6ping-%C3%96stra-Storgatan",
    "district": "Öster",
    "categories": "Shoppa",
    "subCategory": "Health and Beauty",
    "openingTime": "09:00",
    "closingTime": "18:00",
    "contact": {
      "phone": "072-456-7890",
      "email": "info@rituals.com"
    },
    "rating": 5
  },
  {
    "name": "Rizzo",
    "url": "rizzo.se/stores/",
    "district": "Öster",
    "categories": "Shoppa",
    "subCategory": "Apparel",
    "openingTime": "09:00",
    "closingTime": "18:00",
    "contact": {
      "phone": "070-456-7890",
      "email": "info@rizzo.com"
    },
    "rating": 5
  },
  {
    "name": "Röda Korset Second Hand",
    "url": "rodakorset.se/vad-vi-gor/second-hand/butiker/roda-korset-secondhand-jonkoping/?gclid=CjwKCAjwzY2bBhB6EiwAPpUpZvHzKjPuEJP8mzdhkuZYuEUoinVduEX8lEL6C0cnHq-JkG5o4XalYBoCwX8QAvD_BwE",
    "district": "Väster",
    "categories": "Shoppa",
    "subCategory": "Apparel",
    "openingTime": "09:00",
    "closingTime": "18:00",
    "contact": {
      "phone": "073-456-7890",
      "email": "info@email.com"
    },
    "rating": 2
  },
  {
    "name": "Rundquist & Zälle",
    "url": "rundquist-zalle.com",
    "district": "Väster",
    "categories": "Shoppa",
    "subCategory": "Apparel",
    "openingTime": "09:00",
    "closingTime": "18:00",
    "contact": {
      "phone": "072-456-7890",
      "email": "info@rundquistandzälle.com"
    },
    "rating": 4
  },
  {
    "name": "Säfvers Tobak",
    "url": "facebook.com/people/S%C3%A4fvers-tobak/100049803762896/",
    "district": "Öster",
    "categories": "Shoppa",
    "subCategory": "Grocery",
    "openingTime": "09:00",
    "closingTime": "19:00",
    "contact": {
      "phone": "234-456-7890",
      "email": "Säfvers@email.com"
    },
    "rating": 3
  },
  {
    "name": "SåIniNordeN",
    "url": "saininorden.se/",
    "district": "Öster",
    "categories": "Shoppa",
    "subCategory": "Apparel",
    "openingTime": "09:00",
    "closingTime": "18:00",
    "contact": {
      "phone": "123-456-7890",
      "email": "saininorden@email.com"
    },
    "rating": 4
  },
  {
    "name": "Sandströms",
    "url": "sandstroms.nu/butiker/sandstroms-jonkoping",
    "district": "Öster",
    "categories": "Shoppa",
    "subCategory": "Apparel",
    "openingTime": "09:00",
    "closingTime": "18:00",
    "contact": {
      "phone": "765-456-7890",
      "email": "sandstroms@email.com"
    },
    "rating": 5
  },
  {
    "name": "Sarabello",
    "url": "facebook.com/people/SARABELLO/100054240470073/",
    "district": "Öster",
    "categories": "Shoppa",
    "subCategory": "Apparel",
    "openingTime": "09:00",
    "closingTime": "17:00",
    "contact": {
      "phone": "345-456-7890",
      "email": "sarabello@sarabello.com"
    },
    "rating": 4
  },
  {
    "name": "Saumas sko & nyckelservice",
    "url": "saumasskoochnyckelservice.heymo.se/",
    "district": "Väster",
    "categories": "Shoppa",
    "subCategory": "Electronics",
    "openingTime": "12:00",
    "closingTime": "17:00",
    "contact": {
      "phone": "765-456-7890",
      "email": "info@saumasskoochnyckelservice.com"
    },
    "rating": 4
  },
  {
    "name": "Sjöqvists skomakeri",
    "url": "sjoqvistskomakeri.se/",
    "district": "Väster",
    "categories": "Shoppa",
    "subCategory": "Apparel",
    "openingTime": "09:00",
    "closingTime": "18:00",
    "contact": {
      "phone": "876-456-7890",
      "email": "sjoqvistskomakeri@info.com"
    },
    "rating": 3
  },
  {
    "name": "Smålands Skinnmanufaktur",
    "url": "smalandsskinnmanufaktur.se/",
    "district": "Tändsticksområdet",
    "categories": "Shoppa",
    "subCategory": "Home and Decor",
    "openingTime": "09:00",
    "closingTime": "18:00",
    "contact": {
      "phone": "344-456-7890",
      "email": "info@smalandsskinnmanufaktur.com"
    },
    "rating": 5
  },
  {
    "name": "Smarteyes",
    "url": "smarteyes.se/butiker/jonkoping",
    "district": "Öster",
    "categories": "Shoppa",
    "subCategory": "Apparel",
    "openingTime": "09:00",
    "closingTime": "18:00",
    "contact": {
      "phone": "876-456-7890",
      "email": "smarteyes@email.com"
    },
    "rating": 4
  },
  {
    "name": "Smycka Guld",
    "url": "smycka.se/store/19",
    "district": "Öster",
    "categories": "Shoppa",
    "subCategory": "Apparel",
    "openingTime": "09:00",
    "closingTime": "18:00",
    "contact": {
      "phone": "456-456-7890",
      "email": "info@Smycka.com"
    },
    "rating": 5
  },
  {
    "name": "Smycket",
    "url": "smycketjonkoping.se/",
    "district": "Öster",
    "categories": "Shoppa",
    "subCategory": "Apparel",
    "openingTime": "09:00",
    "closingTime": "18:00",
    "contact": {
      "phone": "986-456-7890",
      "email": "smycket@email.com"
    },
    "rating": 5
  },
  {
    "name": "Specsavers",
    "url": "httpspecsavers.se/hitta-till-din-butik/jonkoping-city?utm_source=google&utm_medium=organic&utm_campaign=gmb-website&utm_content=jonkoping&y_source=1_NDA4Nzk2NjQtNzE1LWxvY2F0aW9uLndlYnNpdGU%3D",
    "district": "Öster",
    "categories": "Shoppa",
    "subCategory": "Apparel",
    "openingTime": "09:00",
    "closingTime": "18:00",
    "contact": {
      "phone": "897-456-7890",
      "email": "Specsavers@email.com"
    },
    "rating": 5
  },
  {
    "name": "Stagelight",
    "url": "stagelight.se/",
    "district": "Öster",
    "categories": "Shoppa",
    "subCategory": "Electronics",
    "openingTime": "09:00",
    "closingTime": "19:00",
    "contact": {
      "phone": "907-456-7890",
      "email": "stagelight@email.com"
    },
    "rating": 5
  },
  {
    "name": "Stil",
    "url": "stilbutikerna.se/",
    "district": "Öster",
    "categories": "Shoppa",
    "subCategory": "Apparel",
    "openingTime": "12:00",
    "closingTime": "18:00",
    "contact": {
      "phone": "078-456-7890",
      "email": "example@email.com"
    },
    "rating": 5
  },
  {
    "name": "Story",
    "url": "storyjkpg.se",
    "district": "Atollen",
    "categories": "Shoppa",
    "subCategory": "Apparel",
    "openingTime": "09:00",
    "closingTime": "18:00",
    "contact": {
      "phone": "098-456-7890",
      "email": "Story@email.com"
    },
    "rating": 5
  },
  {
    "name": "SunOff",
    "url": "sunoff.se/butiker/jonkoping?gclid=CjwKCAjw8JKbBhBYEiwAs3sxNy3EnUFGceeFxyJN35fymdpsg5qEWUTPj6Sx0TbNoLdwp8E6AI-I5xoC45gQAvD_BwE",
    "district": "Väster",
    "categories": "Må bra",
    "subCategory": "Beauty Salons and Nail Bars",
    "openingTime": "09:00",
    "closingTime": "18:00",
    "contact": {
      "phone": "890-456-7890",
      "email": "SunOff@SunOff.com"
    },
    "rating": 1
  },
  {
    "name": "Synoptik",
    "url": "httpsynoptik.se/butiker/jonkoping/jonkoping-ostra-storgatan5?utm_campaign=gmb-website&utm_source=google&utm_medium=organic&utm_content=667-Jonkoping-Ostra-Storgatan-5",
    "district": "Öster",
    "categories": "Shoppa",
    "subCategory": "Apparel",
    "openingTime": "09:00",
    "closingTime": "18:00",
    "contact": {
      "phone": "234-456-7890",
      "email": "Synoptik@email.com"
    },
    "rating": 5
  },
  {
    "name": "Synsam Jönköping Öster",
    "url": "synsam.se/optiker/synsam-j%C3%B6nk%C3%B6ping-%C3%B6ster/128",
    "district": "Öster",
    "categories": "Shoppa",
    "subCategory": "Apparel",
    "openingTime": "09:00",
    "closingTime": "14:00",
    "contact": {
      "phone": "890-456-7891",
      "email": "synsam@email.com"
    },
    "rating": 4
  },
  {
    "name": "Synsam Jönköping Väster",
    "url": "synsam.se/optiker/synsam-j%C3%B6nk%C3%B6ping-v%C3%A4ster/125",
    "district": "Väster",
    "categories": "Shoppa",
    "subCategory": "Apparel",
    "openingTime": "09:00",
    "closingTime": "14:00",
    "contact": {
      "phone": "890-456-7890",
      "email": "synsam@email.com"
    },
    "rating": 5
  },
  {
    "name": "Systembolaget",
    "url": "systembolaget.se/butiker-ombud/",
    "district": "Öster",
    "categories": "Shoppa",
    "subCategory": "Grocery",
    "openingTime": "09:00",
    "closingTime": "18:00",
    "contact": {
      "phone": "074-456-7890",
      "email": "systembolaget@email.com"
    },
    "rating": 2
  },
  {
    "name": "The Body Shop",
    "url": "thebodyshop.com/sv-se/store-details/jonkoping-smedjegatan/3801?utm_source=google&utm_medium=organic-local&utm_campaign=yext&utm_content=3801",
    "district": "Öster",
    "categories": "Shoppa",
    "subCategory": "Health and Beauty",
    "openingTime": "09:00",
    "closingTime": "18:00",
    "contact": {
      "phone": "098-456-7890",
      "email": "info@thebodyshop.com"
    },
    "rating": 3
  },
  {
    "name": "Ticket",
    "url": "ticket.se/resebutiker/jonkoping.html",
    "district": "Öster",
    "categories": "Upplev",
    "subCategory": "Entertainment and Activities",
    "openingTime": "07:00",
    "closingTime": "20:00",
    "contact": {
      "phone": "098-456-7890",
      "email": "info@ticket.com"
    },
    "rating": 5
  },
  {
    "name": "Twilfit",
    "url": "shop.change.com/sv-SE",
    "district": "Öster",
    "categories": "Shoppa",
    "subCategory": "Apparel",
    "openingTime": "11:00",
    "closingTime": "19:00",
    "contact": {
      "phone": "083-456-7890",
      "email": "info@Twilfit.com"
    },
    "rating": 5
  },
  {
    "name": "Ur & Penn",
    "url": "uropenn.se/hitta-butik/",
    "district": "Öster",
    "categories": ["Unknown"],
    "subCategory": "Unknown",
    "openingTime": "09:00",
    "closingTime": "18:00",
    "contact": {
      "phone": "123-456-7890",
      "email": "example@email.com"
    },
    "rating": 0,
    "Contact": {
      "phone": "Unknown",
      "email": "unknown@example.com"
    }
  },
  {
    "name": "Västanhem Butik",
    "url": "vastanhem.se",
    "district": "Väster",
    "categories": "Shoppa",
    "subCategory": "Home and Decor",
    "openingTime": "12:00",
    "closingTime": "18:00",
    "contact": {
      "phone": "098-456-7890",
      "email": "vastanhem@email.com"
    },
    "rating": 4
  },
  {
    "name": "Västra klackbaren",
    "url": "Västraklackbaren.com",
    "district": "Öster",
    "categories": "Shoppa",
    "subCategory": "Apparel",
    "openingTime": "09:00",
    "closingTime": "12:00",
    "contact": {
      "phone": "076-456-7890",
      "email": "info@västraklackbaren.com"
    },
    "rating": 3
  },
  {
    "name": "Vätterbygden Ankarbergs Begravningsbyrå",
    "url": "ankarbergs.se/",
    "district": "Väster",
    "categories": "Upplev",
    "subCategory": "Entertainment and Activities",
    "openingTime": "12:00",
    "closingTime": "00:00",
    "contact": {
      "phone": "072-456-7890",
      "email": "ankarbergs@email.com"
    },
    "rating": 5
  },
  {
    "name": "Vätterfisk",
    "url": "xn--vtterfisk-v2a.se/",
    "district": "Väster",
    "categories": "Äta",
    "subCategory": "Restaurants",
    "openingTime": "09:00",
    "closingTime": "20:00",
    "contact": {
      "phone": "123-456-7890",
      "email": "Vätterfisk@email.com"
    },
    "rating": 3
  },
  {
    "name": "Yxhage Lås och Larm",
    "url": "yxhage.se/",
    "district": "Öster",
    "categories": "Shoppa",
    "subCategory": "Electronics",
    "openingTime": "09:00",
    "closingTime": "16:00",
    "contact": {
      "phone": "074-456-7880",
      "email": "info@yxhage.com"
    },
    "rating": 3
  },
  {
    "name": "Zephyr Tattoo Parlour",
    "url": "zephyrtattoo.se",
    "district": "Öster",
    "categories": "Må bra",
    "subCategory": "Beauty Salons and Nail Bars",
    "openingTime": "09:00",
    "closingTime": "18:00",
    "contact": {
      "phone": "073-456-7990",
      "email": "info@zephyrtattoo.com"
    },
    "rating": 4
  }
]
